Workbook

Sheet Pricer
A1: OTC clip pricer: BTC and ETH
A2: Yellow cells are inputs. Everything else is a formula on the data sheets.
A4: Inputs
A5: Asset | B5: BTC | C5: BTC or ETH
A6: Client side | B6: Client buys | C6: Client buys: the desk sells and hedges by buying
A7: Clip size (M$) | B7: 5 | C7: 0.1 to 10 M$ (sizes outside are clipped)
A8: Hour of the request (UTC) | B8: 9 | C8: 0 to 23
A9: Day | B9: Weekday | C9: Weekday or Weekend
A10: Reference mid ($) | B10: =IF($B$5="BTC",83360.83,2506.28) | C10: Last mid recorded; overwrite with the live price
A11: Desk margin (bps) | B11: 2 | C11: Commercial margin added on top of the hedge cost
A12: Participation rate if worked | B12: 0.1 | C12: Share of market volume the desk would take to work the hedge
A13: Confidence (z) | B13: 1.65 | C13: 1.65 = one-sided 95% on the inventory risk
A15: Calculation
A16: Measured window for this hour | B16: =IF(ISNUMBER(MATCH($B$5&"|ALL3|"&IF(AND($B$8>=7,$B$8<12),"London morning",IF(AND($B$8>=12,$B$8<16),"London + New York",IF(AND($B$8>=16,$B$8<21),"New York afternoon","All measured"))),'Sweep costs'!$A$2:$A$25,0)),IF(AND($B$8>=7,$B$8<12),"London morning",IF(AND($B$8>=12,$B$8<16),"London + New York",IF(AND($B$8>=16,$B$8<21),"New York afternoon","All measured"))),"All measured") | C16: Falls back to all measured minutes if this window was not collected
A17: Sweep curve used | B17: =$B$5&"|ALL3|"&B16 | C17: Combined book of Binance, Coinbase and Kraken
A18: Size bracket (index) | B18: =MIN(MATCH(MAX(0.1,MIN(10,$B$7)),'Sweep costs'!$F$1:$K$1,1),5) | C18: Position of the clip between the measured sizes
A19: Sweep cost, combined books (bps) | B19: =INDEX('Sweep costs'!$F$2:$K$25,MATCH(B17,'Sweep costs'!$A$2:$A$25,0),B18)+(MAX(0.1,MIN(10,$B$7))-INDEX('Sweep costs'!$F$1:$K$1,1,B18))*(INDEX('Sweep costs'!$F$2:$K$25,MATCH(B17,'Sweep costs'!$A$2:$A$25,0),B18+1)-INDEX('Sweep costs'!$F$2:$K$25,MATCH(B17,'Sweep costs'!$A$2:$A$25,0),B18))/(INDEX('Sweep costs'!$F$1:$K$1,1,B18+1)-INDEX('Sweep costs'!$F$1:$K$1,1,B18)) | C19: Linear interpolation between measured sizes
A20: Sweep cost, best single venue (bps) | B20: =MIN(INDEX('Sweep costs'!$F$2:$K$25,MATCH($B$5&"|binance|"&B16,'Sweep costs'!$A$2:$A$25,0),B18)+(MAX(0.1,MIN(10,$B$7))-INDEX('Sweep costs'!$F$1:$K$1,1,B18))*(INDEX('Sweep costs'!$F$2:$K$25,MATCH($B$5&"|binance|"&B16,'Sweep costs'!$A$2:$A$25,0),B18+1)-INDEX('Sweep costs'!$F$2:$K$25,MATCH($B$5&"|binance|"&B16,'Sweep costs'!$A$2:$A$25,0),B18))/(INDEX('Sweep costs'!$F$1:$K$1,1,B18+1)-INDEX('Sweep costs'!$F$1:$K$1,1,B18)),INDEX('Sweep costs'!$F$2:$K$25,MATCH($B$5&"|coinbase|"&B16,'Sweep costs'!$A$2:$A$25,0),B18)+(MAX(0.1,MIN(10,$B$7))-INDEX('Sweep costs'!$F$1:$K$1,1,B18))*(INDEX('Sweep costs'!$F$2:$K$25,MATCH($B$5&"|coinbase|"&B16,'Sweep costs'!$A$2:$A$25,0),B18+1)-INDEX('Sweep costs'!$F$2:$K$25,MATCH($B$5&"|coinbase|"&B16,'Sweep costs'!$A$2:$A$25,0),B18))/(INDEX('Sweep costs'!$F$1:$K$1,1,B18+1)-INDEX('Sweep costs'!$F$1:$K$1,1,B18)),INDEX('Sweep costs'!$F$2:$K$25,MATCH($B$5&"|kraken|"&B16,'Sweep costs'!$A$2:$A$25,0),B18)+(MAX(0.1,MIN(10,$B$7))-INDEX('Sweep costs'!$F$1:$K$1,1,B18))*(INDEX('Sweep costs'!$F$2:$K$25,MATCH($B$5&"|kraken|"&B16,'Sweep costs'!$A$2:$A$25,0),B18+1)-INDEX('Sweep costs'!$F$2:$K$25,MATCH($B$5&"|kraken|"&B16,'Sweep costs'!$A$2:$A$25,0),B18))/(INDEX('Sweep costs'!$F$1:$K$1,1,B18+1)-INDEX('Sweep costs'!$F$1:$K$1,1,B18))) | C20: Cheapest of the three venues on its own
A21: Volume at this hour (M$ per minute) | B21: =INDEX('Liquidity clock'!$E$2:$E$97,MATCH($B$5&"|"&$B$9&"|"&$B$8,'Liquidity clock'!$A$2:$A$97,0)) | C21: Binance + Coinbase, six-month median
A22: Volatility at this hour (bps per minute) | B22: =INDEX('Liquidity clock'!$F$2:$F$97,MATCH($B$5&"|"&$B$9&"|"&$B$8,'Liquidity clock'!$A$2:$A$97,0)) | C22: Six-month median
A23: Minutes to work the clip | B23: =MAX(0.1,MIN(10,$B$7))/($B$12*B21) | C23: Clip / (participation x volume)
A24: Risk of working it (bps) | B24: =$B$13*B22*SQRT(B23/3) | C24: z x sigma x sqrt(T / 3): linear liquidation, Almgren-Chriss
A25: Hedge cost retained (bps) | B25: =MIN(B19,B24) | C25: Cheaper of sweeping now or the risk of working it
A26: Hedge method | B26: =IF(B19<=B24,"Sweep the combined books now","Work the order")
A28: Quote
A29: Quoted spread to the client (bps) | B29: =B25+$B$11
A30: Client price ($) | B30: =IF($B$6="Client buys",$B$10*(1+B29/10000),$B$10*(1-B29/10000))
A31: Expected desk P&L on the clip ($) | B31: =$B$11/10000*MAX(0.1,MIN(10,$B$7))*1000000
A32: Saving vs hedging on the best single venue ($) | B32: =(B20-B19)/10000*MAX(0.1,MIN(10,$B$7))*1000000
A34: Sweep costs come from minute snapshots of the displayed books (no hidden liquidity, no refill, no fees). Read them as the cost of an aggressive hedge, not a guaranteed fill.

Sheet Quote grid
A1: Quote grid: spread to quote for an immediate hedge on the combined books (bps)
A2: Spread = measured sweep cost + desk margin (Pricer!B11). Asset follows the Pricer.
A4: Clip (M$) | B4: All measured | C4: London morning | D4: London + New York | E4: New York afternoon
A5: 0.1 | B5: =IFERROR(INDEX('Sweep costs'!$F$2:$K$25,MATCH(Pricer!$B$5&"|ALL3|"&B$4,'Sweep costs'!$A$2:$A$25,0),MATCH($A5,'Sweep costs'!$F$1:$K$1,0))+Pricer!$B$11,"not measured") | C5: =IFERROR(INDEX('Sweep costs'!$F$2:$K$25,MATCH(Pricer!$B$5&"|ALL3|"&C$4,'Sweep costs'!$A$2:$A$25,0),MATCH($A5,'Sweep costs'!$F$1:$K$1,0))+Pricer!$B$11,"not measured") | D5: =IFERROR(INDEX('Sweep costs'!$F$2:$K$25,MATCH(Pricer!$B$5&"|ALL3|"&D$4,'Sweep costs'!$A$2:$A$25,0),MATCH($A5,'Sweep costs'!$F$1:$K$1,0))+Pricer!$B$11,"not measured") | E5: =IFERROR(INDEX('Sweep costs'!$F$2:$K$25,MATCH(Pricer!$B$5&"|ALL3|"&E$4,'Sweep costs'!$A$2:$A$25,0),MATCH($A5,'Sweep costs'!$F$1:$K$1,0))+Pricer!$B$11,"not measured")
A6: 0.5 | B6: =IFERROR(INDEX('Sweep costs'!$F$2:$K$25,MATCH(Pricer!$B$5&"|ALL3|"&B$4,'Sweep costs'!$A$2:$A$25,0),MATCH($A6,'Sweep costs'!$F$1:$K$1,0))+Pricer!$B$11,"not measured") | C6: =IFERROR(INDEX('Sweep costs'!$F$2:$K$25,MATCH(Pricer!$B$5&"|ALL3|"&C$4,'Sweep costs'!$A$2:$A$25,0),MATCH($A6,'Sweep costs'!$F$1:$K$1,0))+Pricer!$B$11,"not measured") | D6: =IFERROR(INDEX('Sweep costs'!$F$2:$K$25,MATCH(Pricer!$B$5&"|ALL3|"&D$4,'Sweep costs'!$A$2:$A$25,0),MATCH($A6,'Sweep costs'!$F$1:$K$1,0))+Pricer!$B$11,"not measured") | E6: =IFERROR(INDEX('Sweep costs'!$F$2:$K$25,MATCH(Pricer!$B$5&"|ALL3|"&E$4,'Sweep costs'!$A$2:$A$25,0),MATCH($A6,'Sweep costs'!$F$1:$K$1,0))+Pricer!$B$11,"not measured")
A7: 1 | B7: =IFERROR(INDEX('Sweep costs'!$F$2:$K$25,MATCH(Pricer!$B$5&"|ALL3|"&B$4,'Sweep costs'!$A$2:$A$25,0),MATCH($A7,'Sweep costs'!$F$1:$K$1,0))+Pricer!$B$11,"not measured") | C7: =IFERROR(INDEX('Sweep costs'!$F$2:$K$25,MATCH(Pricer!$B$5&"|ALL3|"&C$4,'Sweep costs'!$A$2:$A$25,0),MATCH($A7,'Sweep costs'!$F$1:$K$1,0))+Pricer!$B$11,"not measured") | D7: =IFERROR(INDEX('Sweep costs'!$F$2:$K$25,MATCH(Pricer!$B$5&"|ALL3|"&D$4,'Sweep costs'!$A$2:$A$25,0),MATCH($A7,'Sweep costs'!$F$1:$K$1,0))+Pricer!$B$11,"not measured") | E7: =IFERROR(INDEX('Sweep costs'!$F$2:$K$25,MATCH(Pricer!$B$5&"|ALL3|"&E$4,'Sweep costs'!$A$2:$A$25,0),MATCH($A7,'Sweep costs'!$F$1:$K$1,0))+Pricer!$B$11,"not measured")
A8: 2 | B8: =IFERROR(INDEX('Sweep costs'!$F$2:$K$25,MATCH(Pricer!$B$5&"|ALL3|"&B$4,'Sweep costs'!$A$2:$A$25,0),MATCH($A8,'Sweep costs'!$F$1:$K$1,0))+Pricer!$B$11,"not measured") | C8: =IFERROR(INDEX('Sweep costs'!$F$2:$K$25,MATCH(Pricer!$B$5&"|ALL3|"&C$4,'Sweep costs'!$A$2:$A$25,0),MATCH($A8,'Sweep costs'!$F$1:$K$1,0))+Pricer!$B$11,"not measured") | D8: =IFERROR(INDEX('Sweep costs'!$F$2:$K$25,MATCH(Pricer!$B$5&"|ALL3|"&D$4,'Sweep costs'!$A$2:$A$25,0),MATCH($A8,'Sweep costs'!$F$1:$K$1,0))+Pricer!$B$11,"not measured") | E8: =IFERROR(INDEX('Sweep costs'!$F$2:$K$25,MATCH(Pricer!$B$5&"|ALL3|"&E$4,'Sweep costs'!$A$2:$A$25,0),MATCH($A8,'Sweep costs'!$F$1:$K$1,0))+Pricer!$B$11,"not measured")
A9: 5 | B9: =IFERROR(INDEX('Sweep costs'!$F$2:$K$25,MATCH(Pricer!$B$5&"|ALL3|"&B$4,'Sweep costs'!$A$2:$A$25,0),MATCH($A9,'Sweep costs'!$F$1:$K$1,0))+Pricer!$B$11,"not measured") | C9: =IFERROR(INDEX('Sweep costs'!$F$2:$K$25,MATCH(Pricer!$B$5&"|ALL3|"&C$4,'Sweep costs'!$A$2:$A$25,0),MATCH($A9,'Sweep costs'!$F$1:$K$1,0))+Pricer!$B$11,"not measured") | D9: =IFERROR(INDEX('Sweep costs'!$F$2:$K$25,MATCH(Pricer!$B$5&"|ALL3|"&D$4,'Sweep costs'!$A$2:$A$25,0),MATCH($A9,'Sweep costs'!$F$1:$K$1,0))+Pricer!$B$11,"not measured") | E9: =IFERROR(INDEX('Sweep costs'!$F$2:$K$25,MATCH(Pricer!$B$5&"|ALL3|"&E$4,'Sweep costs'!$A$2:$A$25,0),MATCH($A9,'Sweep costs'!$F$1:$K$1,0))+Pricer!$B$11,"not measured")
A10: 10 | B10: =IFERROR(INDEX('Sweep costs'!$F$2:$K$25,MATCH(Pricer!$B$5&"|ALL3|"&B$4,'Sweep costs'!$A$2:$A$25,0),MATCH($A10,'Sweep costs'!$F$1:$K$1,0))+Pricer!$B$11,"not measured") | C10: =IFERROR(INDEX('Sweep costs'!$F$2:$K$25,MATCH(Pricer!$B$5&"|ALL3|"&C$4,'Sweep costs'!$A$2:$A$25,0),MATCH($A10,'Sweep costs'!$F$1:$K$1,0))+Pricer!$B$11,"not measured") | D10: =IFERROR(INDEX('Sweep costs'!$F$2:$K$25,MATCH(Pricer!$B$5&"|ALL3|"&D$4,'Sweep costs'!$A$2:$A$25,0),MATCH($A10,'Sweep costs'!$F$1:$K$1,0))+Pricer!$B$11,"not measured") | E10: =IFERROR(INDEX('Sweep costs'!$F$2:$K$25,MATCH(Pricer!$B$5&"|ALL3|"&E$4,'Sweep costs'!$A$2:$A$25,0),MATCH($A10,'Sweep costs'!$F$1:$K$1,0))+Pricer!$B$11,"not measured")

Sheet Cost of waiting
A1: Cost of waiting: 95% risk of working the clip instead of sweeping (bps)
A2: Clip size, participation and z follow the Pricer. Compare with the sweep cost in the Pricer (a few bps): waiting is the expensive option for every hour.
A4: Hour (UTC) | B4: BTC weekday | C4: BTC weekend | D4: ETH weekday | E4: ETH weekend
A5: 0 | B5: =Pricer!$B$13*INDEX('Liquidity clock'!$F$2:$F$97,MATCH("BTC|Weekday|"&$A5,'Liquidity clock'!$A$2:$A$97,0))*SQRT(MAX(0.1,MIN(10,Pricer!$B$7))/(Pricer!$B$12*INDEX('Liquidity clock'!$E$2:$E$97,MATCH("BTC|Weekday|"&$A5,'Liquidity clock'!$A$2:$A$97,0)))/3) | C5: =Pricer!$B$13*INDEX('Liquidity clock'!$F$2:$F$97,MATCH("BTC|Weekend|"&$A5,'Liquidity clock'!$A$2:$A$97,0))*SQRT(MAX(0.1,MIN(10,Pricer!$B$7))/(Pricer!$B$12*INDEX('Liquidity clock'!$E$2:$E$97,MATCH("BTC|Weekend|"&$A5,'Liquidity clock'!$A$2:$A$97,0)))/3) | D5: =Pricer!$B$13*INDEX('Liquidity clock'!$F$2:$F$97,MATCH("ETH|Weekday|"&$A5,'Liquidity clock'!$A$2:$A$97,0))*SQRT(MAX(0.1,MIN(10,Pricer!$B$7))/(Pricer!$B$12*INDEX('Liquidity clock'!$E$2:$E$97,MATCH("ETH|Weekday|"&$A5,'Liquidity clock'!$A$2:$A$97,0)))/3) | E5: =Pricer!$B$13*INDEX('Liquidity clock'!$F$2:$F$97,MATCH("ETH|Weekend|"&$A5,'Liquidity clock'!$A$2:$A$97,0))*SQRT(MAX(0.1,MIN(10,Pricer!$B$7))/(Pricer!$B$12*INDEX('Liquidity clock'!$E$2:$E$97,MATCH("ETH|Weekend|"&$A5,'Liquidity clock'!$A$2:$A$97,0)))/3)
A6: 1 | B6: =Pricer!$B$13*INDEX('Liquidity clock'!$F$2:$F$97,MATCH("BTC|Weekday|"&$A6,'Liquidity clock'!$A$2:$A$97,0))*SQRT(MAX(0.1,MIN(10,Pricer!$B$7))/(Pricer!$B$12*INDEX('Liquidity clock'!$E$2:$E$97,MATCH("BTC|Weekday|"&$A6,'Liquidity clock'!$A$2:$A$97,0)))/3) | C6: =Pricer!$B$13*INDEX('Liquidity clock'!$F$2:$F$97,MATCH("BTC|Weekend|"&$A6,'Liquidity clock'!$A$2:$A$97,0))*SQRT(MAX(0.1,MIN(10,Pricer!$B$7))/(Pricer!$B$12*INDEX('Liquidity clock'!$E$2:$E$97,MATCH("BTC|Weekend|"&$A6,'Liquidity clock'!$A$2:$A$97,0)))/3) | D6: =Pricer!$B$13*INDEX('Liquidity clock'!$F$2:$F$97,MATCH("ETH|Weekday|"&$A6,'Liquidity clock'!$A$2:$A$97,0))*SQRT(MAX(0.1,MIN(10,Pricer!$B$7))/(Pricer!$B$12*INDEX('Liquidity clock'!$E$2:$E$97,MATCH("ETH|Weekday|"&$A6,'Liquidity clock'!$A$2:$A$97,0)))/3) | E6: =Pricer!$B$13*INDEX('Liquidity clock'!$F$2:$F$97,MATCH("ETH|Weekend|"&$A6,'Liquidity clock'!$A$2:$A$97,0))*SQRT(MAX(0.1,MIN(10,Pricer!$B$7))/(Pricer!$B$12*INDEX('Liquidity clock'!$E$2:$E$97,MATCH("ETH|Weekend|"&$A6,'Liquidity clock'!$A$2:$A$97,0)))/3)
A7: 2 | B7: =Pricer!$B$13*INDEX('Liquidity clock'!$F$2:$F$97,MATCH("BTC|Weekday|"&$A7,'Liquidity clock'!$A$2:$A$97,0))*SQRT(MAX(0.1,MIN(10,Pricer!$B$7))/(Pricer!$B$12*INDEX('Liquidity clock'!$E$2:$E$97,MATCH("BTC|Weekday|"&$A7,'Liquidity clock'!$A$2:$A$97,0)))/3) | C7: =Pricer!$B$13*INDEX('Liquidity clock'!$F$2:$F$97,MATCH("BTC|Weekend|"&$A7,'Liquidity clock'!$A$2:$A$97,0))*SQRT(MAX(0.1,MIN(10,Pricer!$B$7))/(Pricer!$B$12*INDEX('Liquidity clock'!$E$2:$E$97,MATCH("BTC|Weekend|"&$A7,'Liquidity clock'!$A$2:$A$97,0)))/3) | D7: =Pricer!$B$13*INDEX('Liquidity clock'!$F$2:$F$97,MATCH("ETH|Weekday|"&$A7,'Liquidity clock'!$A$2:$A$97,0))*SQRT(MAX(0.1,MIN(10,Pricer!$B$7))/(Pricer!$B$12*INDEX('Liquidity clock'!$E$2:$E$97,MATCH("ETH|Weekday|"&$A7,'Liquidity clock'!$A$2:$A$97,0)))/3) | E7: =Pricer!$B$13*INDEX('Liquidity clock'!$F$2:$F$97,MATCH("ETH|Weekend|"&$A7,'Liquidity clock'!$A$2:$A$97,0))*SQRT(MAX(0.1,MIN(10,Pricer!$B$7))/(Pricer!$B$12*INDEX('Liquidity clock'!$E$2:$E$97,MATCH("ETH|Weekend|"&$A7,'Liquidity clock'!$A$2:$A$97,0)))/3)
A8: 3 | B8: =Pricer!$B$13*INDEX('Liquidity clock'!$F$2:$F$97,MATCH("BTC|Weekday|"&$A8,'Liquidity clock'!$A$2:$A$97,0))*SQRT(MAX(0.1,MIN(10,Pricer!$B$7))/(Pricer!$B$12*INDEX('Liquidity clock'!$E$2:$E$97,MATCH("BTC|Weekday|"&$A8,'Liquidity clock'!$A$2:$A$97,0)))/3) | C8: =Pricer!$B$13*INDEX('Liquidity clock'!$F$2:$F$97,MATCH("BTC|Weekend|"&$A8,'Liquidity clock'!$A$2:$A$97,0))*SQRT(MAX(0.1,MIN(10,Pricer!$B$7))/(Pricer!$B$12*INDEX('Liquidity clock'!$E$2:$E$97,MATCH("BTC|Weekend|"&$A8,'Liquidity clock'!$A$2:$A$97,0)))/3) | D8: =Pricer!$B$13*INDEX('Liquidity clock'!$F$2:$F$97,MATCH("ETH|Weekday|"&$A8,'Liquidity clock'!$A$2:$A$97,0))*SQRT(MAX(0.1,MIN(10,Pricer!$B$7))/(Pricer!$B$12*INDEX('Liquidity clock'!$E$2:$E$97,MATCH("ETH|Weekday|"&$A8,'Liquidity clock'!$A$2:$A$97,0)))/3) | E8: =Pricer!$B$13*INDEX('Liquidity clock'!$F$2:$F$97,MATCH("ETH|Weekend|"&$A8,'Liquidity clock'!$A$2:$A$97,0))*SQRT(MAX(0.1,MIN(10,Pricer!$B$7))/(Pricer!$B$12*INDEX('Liquidity clock'!$E$2:$E$97,MATCH("ETH|Weekend|"&$A8,'Liquidity clock'!$A$2:$A$97,0)))/3)
A9: 4 | B9: =Pricer!$B$13*INDEX('Liquidity clock'!$F$2:$F$97,MATCH("BTC|Weekday|"&$A9,'Liquidity clock'!$A$2:$A$97,0))*SQRT(MAX(0.1,MIN(10,Pricer!$B$7))/(Pricer!$B$12*INDEX('Liquidity clock'!$E$2:$E$97,MATCH("BTC|Weekday|"&$A9,'Liquidity clock'!$A$2:$A$97,0)))/3) | C9: =Pricer!$B$13*INDEX('Liquidity clock'!$F$2:$F$97,MATCH("BTC|Weekend|"&$A9,'Liquidity clock'!$A$2:$A$97,0))*SQRT(MAX(0.1,MIN(10,Pricer!$B$7))/(Pricer!$B$12*INDEX('Liquidity clock'!$E$2:$E$97,MATCH("BTC|Weekend|"&$A9,'Liquidity clock'!$A$2:$A$97,0)))/3) | D9: =Pricer!$B$13*INDEX('Liquidity clock'!$F$2:$F$97,MATCH("ETH|Weekday|"&$A9,'Liquidity clock'!$A$2:$A$97,0))*SQRT(MAX(0.1,MIN(10,Pricer!$B$7))/(Pricer!$B$12*INDEX('Liquidity clock'!$E$2:$E$97,MATCH("ETH|Weekday|"&$A9,'Liquidity clock'!$A$2:$A$97,0)))/3) | E9: =Pricer!$B$13*INDEX('Liquidity clock'!$F$2:$F$97,MATCH("ETH|Weekend|"&$A9,'Liquidity clock'!$A$2:$A$97,0))*SQRT(MAX(0.1,MIN(10,Pricer!$B$7))/(Pricer!$B$12*INDEX('Liquidity clock'!$E$2:$E$97,MATCH("ETH|Weekend|"&$A9,'Liquidity clock'!$A$2:$A$97,0)))/3)
A10: 5 | B10: =Pricer!$B$13*INDEX('Liquidity clock'!$F$2:$F$97,MATCH("BTC|Weekday|"&$A10,'Liquidity clock'!$A$2:$A$97,0))*SQRT(MAX(0.1,MIN(10,Pricer!$B$7))/(Pricer!$B$12*INDEX('Liquidity clock'!$E$2:$E$97,MATCH("BTC|Weekday|"&$A10,'Liquidity clock'!$A$2:$A$97,0)))/3) | C10: =Pricer!$B$13*INDEX('Liquidity clock'!$F$2:$F$97,MATCH("BTC|Weekend|"&$A10,'Liquidity clock'!$A$2:$A$97,0))*SQRT(MAX(0.1,MIN(10,Pricer!$B$7))/(Pricer!$B$12*INDEX('Liquidity clock'!$E$2:$E$97,MATCH("BTC|Weekend|"&$A10,'Liquidity clock'!$A$2:$A$97,0)))/3) | D10: =Pricer!$B$13*INDEX('Liquidity clock'!$F$2:$F$97,MATCH("ETH|Weekday|"&$A10,'Liquidity clock'!$A$2:$A$97,0))*SQRT(MAX(0.1,MIN(10,Pricer!$B$7))/(Pricer!$B$12*INDEX('Liquidity clock'!$E$2:$E$97,MATCH("ETH|Weekday|"&$A10,'Liquidity clock'!$A$2:$A$97,0)))/3) | E10: =Pricer!$B$13*INDEX('Liquidity clock'!$F$2:$F$97,MATCH("ETH|Weekend|"&$A10,'Liquidity clock'!$A$2:$A$97,0))*SQRT(MAX(0.1,MIN(10,Pricer!$B$7))/(Pricer!$B$12*INDEX('Liquidity clock'!$E$2:$E$97,MATCH("ETH|Weekend|"&$A10,'Liquidity clock'!$A$2:$A$97,0)))/3)
A11: 6 | B11: =Pricer!$B$13*INDEX('Liquidity clock'!$F$2:$F$97,MATCH("BTC|Weekday|"&$A11,'Liquidity clock'!$A$2:$A$97,0))*SQRT(MAX(0.1,MIN(10,Pricer!$B$7))/(Pricer!$B$12*INDEX('Liquidity clock'!$E$2:$E$97,MATCH("BTC|Weekday|"&$A11,'Liquidity clock'!$A$2:$A$97,0)))/3) | C11: =Pricer!$B$13*INDEX('Liquidity clock'!$F$2:$F$97,MATCH("BTC|Weekend|"&$A11,'Liquidity clock'!$A$2:$A$97,0))*SQRT(MAX(0.1,MIN(10,Pricer!$B$7))/(Pricer!$B$12*INDEX('Liquidity clock'!$E$2:$E$97,MATCH("BTC|Weekend|"&$A11,'Liquidity clock'!$A$2:$A$97,0)))/3) | D11: =Pricer!$B$13*INDEX('Liquidity clock'!$F$2:$F$97,MATCH("ETH|Weekday|"&$A11,'Liquidity clock'!$A$2:$A$97,0))*SQRT(MAX(0.1,MIN(10,Pricer!$B$7))/(Pricer!$B$12*INDEX('Liquidity clock'!$E$2:$E$97,MATCH("ETH|Weekday|"&$A11,'Liquidity clock'!$A$2:$A$97,0)))/3) | E11: =Pricer!$B$13*INDEX('Liquidity clock'!$F$2:$F$97,MATCH("ETH|Weekend|"&$A11,'Liquidity clock'!$A$2:$A$97,0))*SQRT(MAX(0.1,MIN(10,Pricer!$B$7))/(Pricer!$B$12*INDEX('Liquidity clock'!$E$2:$E$97,MATCH("ETH|Weekend|"&$A11,'Liquidity clock'!$A$2:$A$97,0)))/3)
A12: 7 | B12: =Pricer!$B$13*INDEX('Liquidity clock'!$F$2:$F$97,MATCH("BTC|Weekday|"&$A12,'Liquidity clock'!$A$2:$A$97,0))*SQRT(MAX(0.1,MIN(10,Pricer!$B$7))/(Pricer!$B$12*INDEX('Liquidity clock'!$E$2:$E$97,MATCH("BTC|Weekday|"&$A12,'Liquidity clock'!$A$2:$A$97,0)))/3) | C12: =Pricer!$B$13*INDEX('Liquidity clock'!$F$2:$F$97,MATCH("BTC|Weekend|"&$A12,'Liquidity clock'!$A$2:$A$97,0))*SQRT(MAX(0.1,MIN(10,Pricer!$B$7))/(Pricer!$B$12*INDEX('Liquidity clock'!$E$2:$E$97,MATCH("BTC|Weekend|"&$A12,'Liquidity clock'!$A$2:$A$97,0)))/3) | D12: =Pricer!$B$13*INDEX('Liquidity clock'!$F$2:$F$97,MATCH("ETH|Weekday|"&$A12,'Liquidity clock'!$A$2:$A$97,0))*SQRT(MAX(0.1,MIN(10,Pricer!$B$7))/(Pricer!$B$12*INDEX('Liquidity clock'!$E$2:$E$97,MATCH("ETH|Weekday|"&$A12,'Liquidity clock'!$A$2:$A$97,0)))/3) | E12: =Pricer!$B$13*INDEX('Liquidity clock'!$F$2:$F$97,MATCH("ETH|Weekend|"&$A12,'Liquidity clock'!$A$2:$A$97,0))*SQRT(MAX(0.1,MIN(10,Pricer!$B$7))/(Pricer!$B$12*INDEX('Liquidity clock'!$E$2:$E$97,MATCH("ETH|Weekend|"&$A12,'Liquidity clock'!$A$2:$A$97,0)))/3)
A13: 8 | B13: =Pricer!$B$13*INDEX('Liquidity clock'!$F$2:$F$97,MATCH("BTC|Weekday|"&$A13,'Liquidity clock'!$A$2:$A$97,0))*SQRT(MAX(0.1,MIN(10,Pricer!$B$7))/(Pricer!$B$12*INDEX('Liquidity clock'!$E$2:$E$97,MATCH("BTC|Weekday|"&$A13,'Liquidity clock'!$A$2:$A$97,0)))/3) | C13: =Pricer!$B$13*INDEX('Liquidity clock'!$F$2:$F$97,MATCH("BTC|Weekend|"&$A13,'Liquidity clock'!$A$2:$A$97,0))*SQRT(MAX(0.1,MIN(10,Pricer!$B$7))/(Pricer!$B$12*INDEX('Liquidity clock'!$E$2:$E$97,MATCH("BTC|Weekend|"&$A13,'Liquidity clock'!$A$2:$A$97,0)))/3) | D13: =Pricer!$B$13*INDEX('Liquidity clock'!$F$2:$F$97,MATCH("ETH|Weekday|"&$A13,'Liquidity clock'!$A$2:$A$97,0))*SQRT(MAX(0.1,MIN(10,Pricer!$B$7))/(Pricer!$B$12*INDEX('Liquidity clock'!$E$2:$E$97,MATCH("ETH|Weekday|"&$A13,'Liquidity clock'!$A$2:$A$97,0)))/3) | E13: =Pricer!$B$13*INDEX('Liquidity clock'!$F$2:$F$97,MATCH("ETH|Weekend|"&$A13,'Liquidity clock'!$A$2:$A$97,0))*SQRT(MAX(0.1,MIN(10,Pricer!$B$7))/(Pricer!$B$12*INDEX('Liquidity clock'!$E$2:$E$97,MATCH("ETH|Weekend|"&$A13,'Liquidity clock'!$A$2:$A$97,0)))/3)
A14: 9 | B14: =Pricer!$B$13*INDEX('Liquidity clock'!$F$2:$F$97,MATCH("BTC|Weekday|"&$A14,'Liquidity clock'!$A$2:$A$97,0))*SQRT(MAX(0.1,MIN(10,Pricer!$B$7))/(Pricer!$B$12*INDEX('Liquidity clock'!$E$2:$E$97,MATCH("BTC|Weekday|"&$A14,'Liquidity clock'!$A$2:$A$97,0)))/3) | C14: =Pricer!$B$13*INDEX('Liquidity clock'!$F$2:$F$97,MATCH("BTC|Weekend|"&$A14,'Liquidity clock'!$A$2:$A$97,0))*SQRT(MAX(0.1,MIN(10,Pricer!$B$7))/(Pricer!$B$12*INDEX('Liquidity clock'!$E$2:$E$97,MATCH("BTC|Weekend|"&$A14,'Liquidity clock'!$A$2:$A$97,0)))/3) | D14: =Pricer!$B$13*INDEX('Liquidity clock'!$F$2:$F$97,MATCH("ETH|Weekday|"&$A14,'Liquidity clock'!$A$2:$A$97,0))*SQRT(MAX(0.1,MIN(10,Pricer!$B$7))/(Pricer!$B$12*INDEX('Liquidity clock'!$E$2:$E$97,MATCH("ETH|Weekday|"&$A14,'Liquidity clock'!$A$2:$A$97,0)))/3) | E14: =Pricer!$B$13*INDEX('Liquidity clock'!$F$2:$F$97,MATCH("ETH|Weekend|"&$A14,'Liquidity clock'!$A$2:$A$97,0))*SQRT(MAX(0.1,MIN(10,Pricer!$B$7))/(Pricer!$B$12*INDEX('Liquidity clock'!$E$2:$E$97,MATCH("ETH|Weekend|"&$A14,'Liquidity clock'!$A$2:$A$97,0)))/3)
A15: 10 | B15: =Pricer!$B$13*INDEX('Liquidity clock'!$F$2:$F$97,MATCH("BTC|Weekday|"&$A15,'Liquidity clock'!$A$2:$A$97,0))*SQRT(MAX(0.1,MIN(10,Pricer!$B$7))/(Pricer!$B$12*INDEX('Liquidity clock'!$E$2:$E$97,MATCH("BTC|Weekday|"&$A15,'Liquidity clock'!$A$2:$A$97,0)))/3) | C15: =Pricer!$B$13*INDEX('Liquidity clock'!$F$2:$F$97,MATCH("BTC|Weekend|"&$A15,'Liquidity clock'!$A$2:$A$97,0))*SQRT(MAX(0.1,MIN(10,Pricer!$B$7))/(Pricer!$B$12*INDEX('Liquidity clock'!$E$2:$E$97,MATCH("BTC|Weekend|"&$A15,'Liquidity clock'!$A$2:$A$97,0)))/3) | D15: =Pricer!$B$13*INDEX('Liquidity clock'!$F$2:$F$97,MATCH("ETH|Weekday|"&$A15,'Liquidity clock'!$A$2:$A$97,0))*SQRT(MAX(0.1,MIN(10,Pricer!$B$7))/(Pricer!$B$12*INDEX('Liquidity clock'!$E$2:$E$97,MATCH("ETH|Weekday|"&$A15,'Liquidity clock'!$A$2:$A$97,0)))/3) | E15: =Pricer!$B$13*INDEX('Liquidity clock'!$F$2:$F$97,MATCH("ETH|Weekend|"&$A15,'Liquidity clock'!$A$2:$A$97,0))*SQRT(MAX(0.1,MIN(10,Pricer!$B$7))/(Pricer!$B$12*INDEX('Liquidity clock'!$E$2:$E$97,MATCH("ETH|Weekend|"&$A15,'Liquidity clock'!$A$2:$A$97,0)))/3)
A16: 11 | B16: =Pricer!$B$13*INDEX('Liquidity clock'!$F$2:$F$97,MATCH("BTC|Weekday|"&$A16,'Liquidity clock'!$A$2:$A$97,0))*SQRT(MAX(0.1,MIN(10,Pricer!$B$7))/(Pricer!$B$12*INDEX('Liquidity clock'!$E$2:$E$97,MATCH("BTC|Weekday|"&$A16,'Liquidity clock'!$A$2:$A$97,0)))/3) | C16: =Pricer!$B$13*INDEX('Liquidity clock'!$F$2:$F$97,MATCH("BTC|Weekend|"&$A16,'Liquidity clock'!$A$2:$A$97,0))*SQRT(MAX(0.1,MIN(10,Pricer!$B$7))/(Pricer!$B$12*INDEX('Liquidity clock'!$E$2:$E$97,MATCH("BTC|Weekend|"&$A16,'Liquidity clock'!$A$2:$A$97,0)))/3) | D16: =Pricer!$B$13*INDEX('Liquidity clock'!$F$2:$F$97,MATCH("ETH|Weekday|"&$A16,'Liquidity clock'!$A$2:$A$97,0))*SQRT(MAX(0.1,MIN(10,Pricer!$B$7))/(Pricer!$B$12*INDEX('Liquidity clock'!$E$2:$E$97,MATCH("ETH|Weekday|"&$A16,'Liquidity clock'!$A$2:$A$97,0)))/3) | E16: =Pricer!$B$13*INDEX('Liquidity clock'!$F$2:$F$97,MATCH("ETH|Weekend|"&$A16,'Liquidity clock'!$A$2:$A$97,0))*SQRT(MAX(0.1,MIN(10,Pricer!$B$7))/(Pricer!$B$12*INDEX('Liquidity clock'!$E$2:$E$97,MATCH("ETH|Weekend|"&$A16,'Liquidity clock'!$A$2:$A$97,0)))/3)
... A28: 23 | B28: =Pricer!$B$13*INDEX('Liquidity clock'!$F$2:$F$97,MATCH("BTC|Weekday|"&$A28,'Liquidity clock'!$A$2:$A$97,0))*SQRT(MAX(0.1,MIN(10,Pricer!$B$7))/(Pricer!$B$12*INDEX('Liquidity clock'!$E$2:$E$97,MATCH("BTC|Weekday|"&$A28,'Liquidity clock'!$A$2:$A$97,0)))/3) | C28: =Pricer!$B$13*INDEX('Liquidity clock'!$F$2:$F$97,MATCH("BTC|Weekend|"&$A28,'Liquidity clock'!$A$2:$A$97,0))*SQRT(MAX(0.1,MIN(10,Pricer!$B$7))/(Pricer!$B$12*INDEX('Liquidity clock'!$E$2:$E$97,MATCH("BTC|Weekend|"&$A28,'Liquidity clock'!$A$2:$A$97,0)))/3) | D28: =Pricer!$B$13*INDEX('Liquidity clock'!$F$2:$F$97,MATCH("ETH|Weekday|"&$A28,'Liquidity clock'!$A$2:$A$97,0))*SQRT(MAX(0.1,MIN(10,Pricer!$B$7))/(Pricer!$B$12*INDEX('Liquidity clock'!$E$2:$E$97,MATCH("ETH|Weekday|"&$A28,'Liquidity clock'!$A$2:$A$97,0)))/3) | E28: =Pricer!$B$13*INDEX('Liquidity clock'!$F$2:$F$97,MATCH("ETH|Weekend|"&$A28,'Liquidity clock'!$A$2:$A$97,0))*SQRT(MAX(0.1,MIN(10,Pricer!$B$7))/(Pricer!$B$12*INDEX('Liquidity clock'!$E$2:$E$97,MATCH("ETH|Weekend|"&$A28,'Liquidity clock'!$A$2:$A$97,0)))/3)

Sheet Sweep costs
A1: key | B1: asset | C1: venue | D1: window | E1: minutes | F1: 0.1 | G1: 0.5 | H1: 1 | I1: 2 | J1: 5 | K1: 10
A2: BTC|ALL3|All measured | B2: BTC | C2: ALL3 | D2: All measured | E2: 301 | F2: 0.001 | G2: 0.141 | H2: 0.332 | I2: 0.721 | J2: 1.747 | K2: 3.214
A3: BTC|ALL3|London morning | B3: BTC | C3: ALL3 | D3: London morning | E3: 137 | F3: 0.001 | G3: 0.153 | H3: 0.344 | I3: 0.738 | J3: 1.874 | K3: 3.482
A4: BTC|ALL3|New York afternoon | B4: BTC | C4: ALL3 | D4: New York afternoon | E4: 164 | F4: 0.001 | G4: 0.137 | H4: 0.314 | I4: 0.698 | J4: 1.693 | K4: 3.114
A5: BTC|binance|All measured | B5: BTC | C5: binance | D5: All measured | E5: 301 | F5: 0.001 | G5: 0.563 | H5: 0.955 | I5: 1.677 | J5: 3.53 | K5: 6.654
A6: BTC|binance|London morning | B6: BTC | C6: binance | D6: London morning | E6: 137 | F6: 0.014 | G6: 0.564 | H6: 0.915 | I6: 1.625 | J6: 3.483 | K6: 6.612
A7: BTC|binance|New York afternoon | B7: BTC | C7: binance | D7: New York afternoon | E7: 164 | F7: 0.001 | G7: 0.562 | H7: 0.985 | I7: 1.709 | J7: 3.559 | K7: 6.675
A8: BTC|coinbase|All measured | B8: BTC | C8: coinbase | D8: All measured | E8: 301 | F8: 0.865 | G8: 1.753 | H8: 2.472 | I8: 4.023 | J8: 8.237 | K8: 13.96
A9: BTC|coinbase|London morning | B9: BTC | C9: coinbase | D9: London morning | E9: 137 | F9: 0.973 | G9: 2.098 | H9: 3.212 | I9: 5.35 | J9: 10.99 | K9: 18.442
A10: BTC|coinbase|New York afternoon | B10: BTC | C10: coinbase | D10: New York afternoon | E10: 164 | F10: 0.802 | G10: 1.589 | H10: 2.185 | I10: 3.47 | J10: 7.517 | K10: 13.039
A11: BTC|kraken|All measured | B11: BTC | C11: kraken | D11: All measured | E11: 301 | F11: 0.183 | G11: 0.399 | H11: 0.706 | I11: 1.66 | J11: 4.071 | K11: 7.969
A12: BTC|kraken|London morning | B12: BTC | C12: kraken | D12: London morning | E12: 137 | F12: 0.214 | G12: 0.447 | H12: 0.785 | I12: 1.781 | J12: 4.259 | K12: 8.089
A13: BTC|kraken|New York afternoon | B13: BTC | C13: kraken | D13: New York afternoon | E13: 164 | F13: 0.158 | G13: 0.368 | H13: 0.658 | I13: 1.564 | J13: 3.953 | K13: 7.837
... A25: ETH|kraken|New York afternoon | B25: ETH | C25: kraken | D25: New York afternoon | E25: 164 | F25: 0.968 | G25: 2.016 | H25: 2.925 | I25: 4.402 | J25: 9.484 | K25: 19.844
A27: Median cost of sweeping the displayed book, bps vs the venue's own mid, average of buy and sell. Columns are clip sizes in M$.

Sheet Liquidity clock
A1: key | B1: asset | C1: day | D1: hour | E1: vol_per_min_musd | F1: sigma_1m_bps | G1: coinbase_share | H1: days
A2: BTC|Weekday|0 | B2: BTC | C2: Weekday | D2: 0 | E2: 0.9684 | F2: 4.672 | G2: 0.265 | H2: 139
A3: BTC|Weekday|1 | B3: BTC | C3: Weekday | D3: 1 | E3: 0.9504 | F3: 4.965 | G3: 0.267 | H3: 139
A4: BTC|Weekday|2 | B4: BTC | C4: Weekday | D4: 2 | E4: 0.8837 | F4: 4.467 | G4: 0.266 | H4: 139
A5: BTC|Weekday|3 | B5: BTC | C5: Weekday | D5: 3 | E5: 0.7688 | F5: 3.893 | G5: 0.242 | H5: 139
A6: BTC|Weekday|4 | B6: BTC | C6: Weekday | D6: 4 | E6: 0.8077 | F6: 3.543 | G6: 0.223 | H6: 139
A7: BTC|Weekday|5 | B7: BTC | C7: Weekday | D7: 5 | E7: 0.853 | F7: 3.818 | G7: 0.209 | H7: 139
A8: BTC|Weekday|6 | B8: BTC | C8: Weekday | D8: 6 | E8: 0.841 | F8: 3.761 | G8: 0.207 | H8: 139
A9: BTC|Weekday|7 | B9: BTC | C9: Weekday | D9: 7 | E9: 1.1373 | F9: 3.83 | G9: 0.164 | H9: 139
A10: BTC|Weekday|8 | B10: BTC | C10: Weekday | D10: 8 | E10: 0.9827 | F10: 4.16 | G10: 0.22 | H10: 139
A11: BTC|Weekday|9 | B11: BTC | C11: Weekday | D11: 9 | E11: 0.88 | F11: 3.675 | G11: 0.22 | H11: 139
A12: BTC|Weekday|10 | B12: BTC | C12: Weekday | D12: 10 | E12: 0.7707 | F12: 3.781 | G12: 0.256 | H12: 139
A13: BTC|Weekday|11 | B13: BTC | C13: Weekday | D13: 11 | E13: 0.8336 | F13: 3.693 | G13: 0.275 | H13: 139
... A97: ETH|Weekend|23 | B97: ETH | C97: Weekend | D97: 23 | E97: 0.3324 | F97: 4.984 | G97: 0.237 | H97: 56
A99: Median over days of the hourly mean of Binance + Coinbase volume (M$ per minute) and of the RMS 1-minute log return (bps). 1 Apr to 12 Oct 2026.

Sheet Notes
A1: How to read this workbook
A2: Pricer: one client request in, one quote out. Change the yellow cells.
A3: Quote grid: the same quote for every measured size and session.
A4: Cost of waiting: what the desk would risk by working the clip at a share of volume instead of sweeping.
A6: Data
A7: Sweep costs: 301 one-minute snapshots of the Binance (BTCUSDT, ETHUSDT), Coinbase and Kraken (BTC-USD, ETH-USD) books, 12 Oct 17:23 to 13 Oct 09:28 UTC.
A8: Liquidity clock: Binance and Coinbase 1-minute candles, 1 April to 12 October 2026.
A9: Costs are in bps of each venue's own mid, so the USDT/USD basis between Binance and the USD venues cancels out.
A11: Limits
A12: Displayed liquidity only: no hidden orders, no book refill after a sweep, no fees, no market-maker fade.
A13: Asia was not measured in the books; for those hours the Pricer uses all measured minutes.
A14: Volume excludes Kraken and every other venue, so the time to work a clip is conservative.
